edge_orm/__init__.py
edge_orm/cache.py
edge_orm/errors.py
edge_orm/execute.py
edge_orm/execute_regex.py
edge_orm/external/encoders.py
edge_orm/helpers.py
edge_orm/logs.py
edge_orm/node/__init__.py
edge_orm/node/errors.py
edge_orm/node/models.py
edge_orm/resolver/__init__.py
edge_orm/resolver/enums.py
edge_orm/resolver/errors.py
edge_orm/resolver/merging.py
edge_orm/resolver/model.py
edge_orm/resolver/nested_resolvers.py
edge_orm/resolver/utils.py
edge_orm/span.py
edge_orm/types_generator/__init__.py
edge_orm/types_generator/introspection.py
edge_orm/types_generator/main.py
edge_orm/unset.py
edge_orm/validators.py
edge_orm-0.10.3.dist-info/METADATA
edge_orm-0.10.3.dist-info/WHEEL
edge_orm-0.10.3.dist-info/RECORD
